pypyr_scheduler_server-2.0.7-py3.8-nspkg.pth
pypyr_scheduler_server-2.0.7.data/data/conf/scheduler_config.py
pyrsched/server/__init__.py
pyrsched/server/__main__.py
pyrsched/server/cli.py
pyrsched/server/logging.py
pyrsched/server/server.py
pyrsched/server/service.py
pyrsched/server/utils.py
pypyr_scheduler_server-2.0.7.dist-info/LICENSE
pypyr_scheduler_server-2.0.7.dist-info/METADATA
pypyr_scheduler_server-2.0.7.dist-info/WHEEL
pypyr_scheduler_server-2.0.7.dist-info/namespace_packages.txt
pypyr_scheduler_server-2.0.7.dist-info/top_level.txt
pypyr_scheduler_server-2.0.7.dist-info/RECORD
