Metadata-Version: 2.1
Name: pypyr-scheduler-server
Version: 2.0.7
Summary: Schedule pypyr pipelines with apscheduler
Home-page: https://github.com/pypyr-scheduler/pypyr-scheduler-server
Author: David Zerrenner
Author-email: dazer017@gmail.com
License: MIT
Keywords: Pypyr,Scheduler,Taskrunner
Platform: UNKNOWN
Classifier: Development Status :: 5 - Production/Stable
Classifier: Intended Audience :: Developers
Classifier: Intended Audience :: System Administrators
Classifier: License :: OSI Approved :: MIT License
Classifier: Programming Language :: Python
Classifier: Programming Language :: Python :: 3.8
Requires-Dist: apscheduler
Requires-Dist: pytz
Requires-Dist: psutil
Requires-Dist: click
Requires-Dist: pypyr
